<?xml version="1.0" encoding="UTF-8"?>
<jcr:root xmlns:sling="http://sling.apache.org/jcr/sling/1.0" xmlns:cq="http://www.day.com/jcr/cq/1.0" xmlns:jcr="http://www.jcp.org/jcr/1.0" xmlns:nt="http://www.jcp.org/jcr/nt/1.0"
    jcr:primaryType="nt:unstructured"
    sling:resourceType="cq/gui/components/authoring/dialog">
    <content
        jcr:primaryType="nt:unstructured"
        sling:resourceType="granite/ui/components/coral/foundation/container">
        <items jcr:primaryType="nt:unstructured">
            <mytabs
                jcr:primaryType="nt:unstructured"
                sling:resourceType="granite/ui/components/coral/foundation/tabs">
                <items jcr:primaryType="nt:unstructured">
                    <tab1
                        jcr:primaryType="nt:unstructured"
                        jcr:title="loo"
                        sling:resourceType="granite/ui/components/coral/foundation/container">
                        <items jcr:primaryType="nt:unstructured">
                            <columns
                                jcr:primaryType="nt:unstructured"
                                sling:resourceType="granite/ui/components/coral/foundation/fixedcolumns">
                                <items jcr:primaryType="nt:unstructured">
                                    <column
                                        jcr:primaryType="nt:unstructured"
                                        sling:resourceType="granite/ui/components/coral/foundation/container">
                                        <items jcr:primaryType="nt:unstructured">
                                            <image
                                                jcr:primaryType="nt:unstructured"
                                                sling:resourceType="cq/gui/components/authoring/dialog/fileupload"
                                                autoStart="{Boolean}false"
                                                class="cq-droptarget"
                                                fileNameParameter="./fileName"
                                                fileReferenceParameter="./fileReference"
                                                mimeTypes="[image]"
                                                multiple="{Boolean}false"
                                                name="./image"
                                                title="Upload Image Asset"
                                                uploadUrl="${suffix.path}"
                                                useHTML5="{Boolean}true"/>
                                            <title
                                                jcr:primaryType="nt:unstructured"
                                                sling:resourceType="granite/ui/components/coral/foundation/form/textfield"
                                                fieldDescription="title"
                                                fieldLabel="title"
                                                name="./title"
                                                required="{Boolean}true"/>
                                            <action
                                                jcr:primaryType="nt:unstructured"
                                                sling:resourceType="granite/ui/components/coral/foundation/form/pathbrowser"
                                                fieldDescription="Action"
                                                fieldLabel="Action Field"
                                                name="./action"/>
                                            <description
                                                jcr:primaryType="nt:unstructured"
                                                sling:resourceType="granite/ui/components/coral/foundation/form/textarea"
                                                fieldDescription="Description"
                                                fieldLabel="Description"
                                                name="./description"
                                                required="{Boolean}true"/>
                                            <color
                                                jcr:primaryType="nt:unstructured"
                                                sling:resourceType="granite/ui/components/coral/foundation/form/colorfield"
                                                fieldDescription="color"
                                                fieldLabel="background color"
                                                name="./color"
                                                required="{Boolean}true"/>
                                            <buttonTitle
                                                jcr:primaryType="nt:unstructured"
                                                sling:resourceType="granite/ui/components/coral/foundation/form/textfield"
                                                fieldDescription="buttonTitle"
                                                fieldLabel="buttonTitle"
                                                name="./buttonTitle"/>
                                            <buttonAction
                                                jcr:primaryType="nt:unstructured"
                                                sling:resourceType="granite/ui/components/coral/foundation/form/pathbrowser"
                                                fieldDescription="Button Action"
                                                fieldLabel="Button Action Field"
                                                name="./buttonAction"/>
                                        </items>
                                    </column>
                                </items>
                            </columns>
                        </items>
                    </tab1>
                </items>
            </mytabs>
        </items>
    </content>
</jcr:root>
